jupyterstan/__init__.py
jupyterstan-0.1.3.data/data/etc/jupyter/nbconfig/notebook.d/stan_syntax.json
jupyterstan-0.1.3.dist-info/METADATA
jupyterstan-0.1.3.dist-info/RECORD
jupyterstan-0.1.3.dist-info/WHEEL
jupyterstan-0.1.3.dist-info/top_level.txt
stan_syntax/__init__.py
stan_syntax/static/stan_syntax/README.md
stan_syntax/static/stan_syntax/configurator.yaml
stan_syntax/static/stan_syntax/main.js
stan_syntax/static/stan_syntax/stan.css
stan_syntax/static/stan_syntax/stan.js
