Metadata-Version: 2.1
Name: jupyterstan
Version: 0.1.3
Summary: Magics for defining stan code in notebooks.
Home-page: https://github.com/janfreyberg/jupyterstan
Author: Jan Freyberg
Author-email: jan.freyberg@gmail.com
License: UNKNOWN
Platform: UNKNOWN
Classifier: Development Status :: 3 - Alpha
Classifier: Framework :: IPython
Classifier: Intended Audience :: Developers
Classifier: Operating System :: OS Independent
Classifier: Programming Language :: Python
Classifier: Programming Language :: Python :: 2
Classifier: Programming Language :: Python :: 2.7
Classifier: Programming Language :: Python :: 3
Classifier: Programming Language :: Python :: 3.6
Classifier: Topic :: Software Development :: Libraries :: Python Modules
Requires-Dist: ipython
Requires-Dist: pystan
Requires-Dist: humanize
